tjson/__init__.py
tjson/main.py
tjson/controller/__init__.py
tjson/controller/build_tree.py
tjson/controller/search.py
tjson/util/__init__.py
tjson/util/load_json.py
tjson/view/__init__.py
tjson/view/search_screen.py
tjson/view/tjson.py
tuijson-0.1.2.dist-info/METADATA
tuijson-0.1.2.dist-info/WHEEL
tuijson-0.1.2.dist-info/entry_points.txt
tuijson-0.1.2.dist-info/top_level.txt
tuijson-0.1.2.dist-info/RECORD
