Metadata-Version: 2.4
Name: tuijson
Version: 0.1.2
Summary: Open a JSON file or load a JSON string and traverse it as a collapsable tree.
Requires-Python: >=3.12
Requires-Dist: jsondiff>=2.2.1
Requires-Dist: textual>=6.7.0
Provides-Extra: test
Requires-Dist: pytest; extra == "test"
Provides-Extra: build
Requires-Dist: shiv; extra == "build"
